<?xml version="1.0" encoding="utf-8"?>
<ufinterface sender="001" receiver="u8" roottag="bom" docid="216930568" proc="query" codeexchanged="N" exportneedexch="N" paginate="0" display="物料清单" family="生产制造" dynamicdate="9/27/2018" maxdataitems="20000" bignoreextenduserdefines="y" timestamp="0x00000000004B1297" lastquerydate="2018-09-27 17:16:50">
	<Bom><Version><BomId>1000000023</BomId><BomType>1</BomType><Version>20</Version><VersionDesc>11</VersionDesc><VersionEffDate>2018-09-27T00:00:00+08:00</VersionEffDate><Status>1</Status><Ufts>AAAAAABLEo0=</Ufts></Version><Parent><BomId>1000000023</BomId><InvCode>1001212</InvCode><InvName>零部件112</InvName><Free8></Free8><ParentScrap>0.000</ParentScrap></Parent><Component><OpComponentId>1000000068</OpComponentId><BomId>1000000023</BomId><SortSeq>20</SortSeq><OpSeq>0000</OpSeq><InvCode>01010002</InvCode><Free8></Free8><EffBegDate>2018-09-27T00:00:00+08:00</EffBegDate><EffEndDate>2099-12-31T00:00:00+08:00</EffEndDate><FVFlag>1</FVFlag><BaseQtyN>1.000000</BaseQtyN><BaseQtyD>1.000000</BaseQtyD><CompScrap>0.000</CompScrap><ByproductFlag>false</ByproductFlag><OptionsId>1000000068</OptionsId><ProductType>1</ProductType></Component><Component><OpComponentId>1000000067</OpComponentId><BomId>1000000023</BomId><SortSeq>10</SortSeq><OpSeq>0000</OpSeq><InvCode>01010003</InvCode><Free8></Free8><EffBegDate>2018-09-27T00:00:00+08:00</EffBegDate><EffEndDate>2099-12-31T00:00:00+08:00</EffEndDate><FVFlag>1</FVFlag><BaseQtyN>1.000000</BaseQtyN><BaseQtyD>1.000000</BaseQtyD><CompScrap>0.000</CompScrap><ByproductFlag>false</ByproductFlag><OptionsId>1000000067</OptionsId><ProductType>1</ProductType></Component><ComponentOpt><OptionsId>1000000067</OptionsId><Offset>0</Offset><WIPType>3</WIPType><AccuCostFlag>true</AccuCostFlag><OptionalFlag>false</OptionalFlag><MutexRule>2</MutexRule><PlanFactor>100.000</PlanFactor><CostWIPRel>false</CostWIPRel></ComponentOpt><ComponentOpt><OptionsId>1000000068</OptionsId><Offset>0</Offset><WIPType>3</WIPType><AccuCostFlag>true</AccuCostFlag><OptionalFlag>false</OptionalFlag><MutexRule>2</MutexRule><PlanFactor>100.000</PlanFactor><CostWIPRel>false</CostWIPRel></ComponentOpt></Bom></ufinterface>
